{
	"info": {
		"_postman_id": "44534e4c-fd36-4238-a42a-4f4007362148",
		"name": "Secret Santa",
		"schema": "https://schema.getpostman.com/json/collection/v2.1.0/collection.json",
		"_exporter_id": "21082764",
		"_collection_link": "https://galactic-meadow-661390.postman.co/workspace/i-tips~6a07f29c-04d7-4da7-8afd-b710cc486807/collection/21082764-44534e4c-fd36-4238-a42a-4f4007362148?action=share&source=collection_link&creator=21082764"
	},
	"item": [
		{
			"name": "Users",
			"item": [
				{
					"name": "ListenAllUsers",
					"request": {
						"method": "GET",
						"header": [],
						"url": {
							"raw": "localhost:3003/users",
							"host": [
								"localhost"
							],
							"port": "3003",
							"path": [
								"users"
							]
						}
					},
					"response": []
				},
				{
					"name": "Register",
					"request": {
						"method": "POST",
						"header": [],
						"body": {
							"mode": "urlencoded",
							"urlencoded": [
								{
									"key": "email",
									"value": "lecerf@gmail.com",
									"type": "text"
								},
								{
									"key": "password",
									"value": "123",
									"type": "text"
								}
							]
						},
						"url": {
							"raw": "localhost:3003/users/register",
							"host": [
								"localhost"
							],
							"port": "3003",
							"path": [
								"users",
								"register"
							]
						}
					},
					"response": []
				},
				{
					"name": "Login",
					"request": {
						"method": "POST",
						"header": [
							{
								"key": "Authorization",
								"value": "eyJhbGciOiJIUzI1NiIsInR5cCI6IkpXVCJ9.eyJpZCI6IjY1N2IyNDU1ZjhkODUwYzJiNjdkMTNiNSIsImVtYWlsIjoiY2VjZTFAZ21haWwuY290dCIsImlhdCI6MTcwMjU2OTA0OCwiZXhwIjoxNzAyNjA1MDQ4fQ.bgjcoN8FUZGDv6OsdpuQPw6-tNiNjKS8vKE8ewWWp9s",
								"type": "text",
								"disabled": true
							}
						],
						"body": {
							"mode": "urlencoded",
							"urlencoded": [
								{
									"key": "email",
									"value": "cece@gmail.com",
									"type": "text"
								},
								{
									"key": "password",
									"value": "123",
									"type": "text"
								}
							]
						},
						"url": {
							"raw": "localhost:3003/users/login",
							"host": [
								"localhost"
							],
							"port": "3003",
							"path": [
								"users",
								"login"
							]
						}
					},
					"response": []
				},
				{
					"name": "OneUser",
					"request": {
						"method": "GET",
						"header": [
							{
								"key": "Authorization",
								"value": "eyJhbGciOiJIUzI1NiIsInR5cCI6IkpXVCJ9.eyJpZCI6IjY1N2Y1YWJjOGQzNjNjZTc3MGQwZmQwZiIsImVtYWlsIjoiY2VjaWxlQGdtYWlsLmNvbSIsImlhdCI6MTcwMjg0NTE0OCwiZXhwIjoxNzAyODgxMTQ4fQ.LhbFQcJsglpVkmviy5dCzRRcDItWHueGxcSpPZpOST4",
								"type": "text"
							}
						],
						"url": {
							"raw": "localhost:3003/users/657f5abc8d363ce770d0fd0f",
							"host": [
								"localhost"
							],
							"port": "3003",
							"path": [
								"users",
								"657f5abc8d363ce770d0fd0f"
							]
						}
					},
					"response": []
				},
				{
					"name": "UpdateUser",
					"request": {
						"method": "PUT",
						"header": [
							{
								"key": "Authorization",
								"value": "eyJhbGciOiJIUzI1NiIsInR5cCI6IkpXVCJ9.eyJpZCI6IjY1N2IyNDU1ZjhkODUwYzJiNjdkMTNiNSIsImVtYWlsIjoiY2VjZTFAZ21haWwuY290dCIsImlhdCI6MTcwMjU2OTA0OCwiZXhwIjoxNzAyNjA1MDQ4fQ.bgjcoN8FUZGDv6OsdpuQPw6-tNiNjKS8vKE8ewWWp9s",
								"type": "text"
							}
						],
						"body": {
							"mode": "urlencoded",
							"urlencoded": [
								{
									"key": "email",
									"value": "cece@gmail.com",
									"type": "text"
								},
								{
									"key": "password",
									"value": "12",
									"type": "text"
								}
							]
						},
						"url": {
							"raw": "localhost:3003/users/657b2455f8d850c2b67d13b5",
							"host": [
								"localhost"
							],
							"port": "3003",
							"path": [
								"users",
								"657b2455f8d850c2b67d13b5"
							]
						}
					},
					"response": []
				},
				{
					"name": "DeleteUser",
					"request": {
						"method": "DELETE",
						"header": [
							{
								"key": "Authorization",
								"value": "eyJhbGciOiJIUzI1NiIsInR5cCI6IkpXVCJ9.eyJpZCI6IjY1N2Y1YWQyOGQzNjNjZTc3MGQwZmQxNyIsImVtYWlsIjoicm9iaW5AZ21haWwuY29tIiwiaWF0IjoxNzAyODQ2ODY0LCJleHAiOjE3MDI4ODI4NjR9.bea3BlC3f1WAACVchqIu-Y6MAF4b27GrG-IMXzI07so",
								"type": "text"
							}
						],
						"url": {
							"raw": "localhost:3003/users/657f5ad28d363ce770d0fd17",
							"host": [
								"localhost"
							],
							"port": "3003",
							"path": [
								"users",
								"657f5ad28d363ce770d0fd17"
							]
						}
					},
					"response": []
				}
			]
		},
		{
			"name": "Groups",
			"item": [
				{
					"name": "ListenAllGroups",
					"request": {
						"method": "GET",
						"header": [],
						"url": {
							"raw": "localhost:3003/groups",
							"host": [
								"localhost"
							],
							"port": "3003",
							"path": [
								"groups"
							]
						}
					},
					"response": []
				},
				{
					"name": "CreateGroup",
					"request": {
						"method": "POST",
						"header": [
							{
								"key": "Authorization",
								"value": "eyJhbGciOiJIUzI1NiIsInR5cCI6IkpXVCJ9.eyJpZCI6IjY1N2Y1YWJjOGQzNjNjZTc3MGQwZmQwZiIsImVtYWlsIjoiY2VjaWxlQGdtYWlsLmNvbSIsImlhdCI6MTcwMjg0NTE0OCwiZXhwIjoxNzAyODgxMTQ4fQ.LhbFQcJsglpVkmviy5dCzRRcDItWHueGxcSpPZpOST4",
								"type": "text"
							}
						],
						"body": {
							"mode": "urlencoded",
							"urlencoded": [
								{
									"key": "name",
									"value": "rose",
									"type": "text"
								},
								{
									"key": "admin",
									"value": "657c57483159ebcad5a3a32c",
									"type": "text"
								}
							]
						},
						"url": {
							"raw": "localhost:3003/groups",
							"host": [
								"localhost"
							],
							"port": "3003",
							"path": [
								"groups"
							]
						}
					},
					"response": []
				},
				{
					"name": "Update Group",
					"request": {
						"method": "PUT",
						"header": [
							{
								"key": "Authorization",
								"value": "eyJhbGciOiJIUzI1NiIsInR5cCI6IkpXVCJ9.eyJpZCI6IjY1N2M1NzQ4MzE1OWViY2FkNWEzYTMyYyIsImVtYWlsIjoiY2VjaWxlQGdtYWlsLmNvbSIsImlhdCI6MTcwMjY0NzY0NSwiZXhwIjoxNzAyNjgzNjQ1fQ.wlmNDkf548BC8_U2e0yP58hfeJBqFaYSwn57KvlVz5Y",
								"type": "text"
							}
						],
						"body": {
							"mode": "urlencoded",
							"urlencoded": [
								{
									"key": "name",
									"value": "rose",
									"type": "text"
								},
								{
									"key": "admin",
									"value": "657c57483159ebcad5a3a32c",
									"type": "text"
								},
								{
									"key": "user_id",
									"value": "",
									"type": "text"
								}
							]
						},
						"url": {
							"raw": "localhost:3003/group/update/657c373d1dc1a92c594d7bf6",
							"host": [
								"localhost"
							],
							"port": "3003",
							"path": [
								"group",
								"update",
								"657c373d1dc1a92c594d7bf6"
							]
						}
					},
					"response": []
				},
				{
					"name": "OneGroup",
					"request": {
						"method": "GET",
						"header": [
							{
								"key": "Authorization",
								"value": "eyJhbGciOiJIUzI1NiIsInR5cCI6IkpXVCJ9.eyJpZCI6IjY1N2Y1YWJjOGQzNjNjZTc3MGQwZmQwZiIsImVtYWlsIjoiY2VjaWxlQGdtYWlsLmNvbSIsImlhdCI6MTcwMjg0NTE0OCwiZXhwIjoxNzAyODgxMTQ4fQ.LhbFQcJsglpVkmviy5dCzRRcDItWHueGxcSpPZpOST4",
								"type": "text"
							}
						],
						"url": {
							"raw": "localhost:3003/group/657f5c6565ca9d288d9281e4",
							"host": [
								"localhost"
							],
							"port": "3003",
							"path": [
								"group",
								"657f5c6565ca9d288d9281e4"
							]
						}
					},
					"response": []
				},
				{
					"name": "Delete group",
					"request": {
						"method": "POST",
						"header": [
							{
								"key": "Authorization",
								"value": "eyJhbGciOiJIUzI1NiIsInR5cCI6IkpXVCJ9.eyJpZCI6IjY1N2MzMzc2MjZlZmZhYzgzYWNjMGExOCIsImVtYWlsIjoiY2VjZUBnbWFpbC5jb3R0byIsImlhdCI6MTcwMjYzOTM2MiwiZXhwIjoxNzAyNjc1MzYyfQ.8gcF_kk7QJCHWfrJzF5r70jG5KL6D6Sm60Xb4j24odE",
								"type": "text"
							}
						],
						"body": {
							"mode": "urlencoded",
							"urlencoded": [
								{
									"key": "user_id",
									"value": "",
									"type": "text"
								}
							]
						},
						"url": {
							"raw": "localhost:3003/group/delete/657c373d1dc1a92c594d7bf6",
							"host": [
								"localhost"
							],
							"port": "3003",
							"path": [
								"group",
								"delete",
								"657c373d1dc1a92c594d7bf6"
							]
						}
					},
					"response": []
				}
			]
		},
		{
			"name": "MemberShip",
			"item": [
				{
					"name": "Invite",
					"request": {
						"method": "POST",
						"header": [
							{
								"key": "Authorization",
								"value": "eyJhbGciOiJIUzI1NiIsInR5cCI6IkpXVCJ9.eyJpZCI6IjY1N2Y1YWJjOGQzNjNjZTc3MGQwZmQwZiIsImVtYWlsIjoiY2VjaWxlQGdtYWlsLmNvbSIsImlhdCI6MTcwMjg0NTE0OCwiZXhwIjoxNzAyODgxMTQ4fQ.LhbFQcJsglpVkmviy5dCzRRcDItWHueGxcSpPZpOST4",
								"type": "text"
							}
						],
						"body": {
							"mode": "urlencoded",
							"urlencoded": [
								{
									"key": "email",
									"value": "lecerf@gmail.com",
									"type": "text"
								}
							]
						},
						"url": {
							"raw": "localhost:3003/group/invite/657f5c6565ca9d288d9281e4/657c57483159ebcad5a3a32c",
							"host": [
								"localhost"
							],
							"port": "3003",
							"path": [
								"group",
								"invite",
								"657f5c6565ca9d288d9281e4",
								"657c57483159ebcad5a3a32c"
							]
						}
					},
					"response": []
				},
				{
					"name": "Accept",
					"request": {
						"method": "POST",
						"header": [],
						"body": {
							"mode": "urlencoded",
							"urlencoded": [
								{
									"key": "accept",
									"value": "true",
									"type": "text"
								},
								{
									"key": "tokenGroup",
									"value": "eyJhbGciOiJIUzI1NiIsInR5cCI6IkpXVCJ9.eyJpZCI6IjY1N2Y1ZjhiZjNkNjJlZmUwZGM3MThkNCIsImdyb3VwX2lkIjoiNjU3ZjVjNjU2NWNhOWQyODhkOTI4MWU0IiwidXNlcl9pZCI6IjY1N2Y1YWM3OGQzNjNjZTc3MGQwZmQxMyIsImlhdCI6MTcwMjg0NjM0NywiZXhwIjoxNzAyODgyMzQ3fQ.SVFiDWD-fIVugTHCbdewdE6LE1GpvWjr9cicTfzr9Wo",
									"type": "text"
								}
							]
						},
						"url": {
							"raw": "localhost:3003/group/accept/657f5c6565ca9d288d9281e4/657f5ac78d363ce770d0fd13",
							"host": [
								"localhost"
							],
							"port": "3003",
							"path": [
								"group",
								"accept",
								"657f5c6565ca9d288d9281e4",
								"657f5ac78d363ce770d0fd13"
							]
						}
					},
					"response": []
				},
				{
					"name": "Draw",
					"request": {
						"method": "GET",
						"header": [
							{
								"key": "Authorization",
								"value": "eyJhbGciOiJIUzI1NiIsInR5cCI6IkpXVCJ9.eyJpZCI6IjY1N2Y1YWJjOGQzNjNjZTc3MGQwZmQwZiIsImVtYWlsIjoiY2VjaWxlQGdtYWlsLmNvbSIsImlhdCI6MTcwMjg0NTE0OCwiZXhwIjoxNzAyODgxMTQ4fQ.LhbFQcJsglpVkmviy5dCzRRcDItWHueGxcSpPZpOST4",
								"type": "text"
							}
						],
						"url": {
							"raw": "localhost:3003/group/draw/657f5c6565ca9d288d9281e4/657c57483159ebcad5a3a32c",
							"host": [
								"localhost"
							],
							"port": "3003",
							"path": [
								"group",
								"draw",
								"657f5c6565ca9d288d9281e4",
								"657c57483159ebcad5a3a32c"
							]
						}
					},
					"response": []
				},
				{
					"name": "All Members Of A Group",
					"request": {
						"method": "GET",
						"header": [
							{
								"key": "Authorization",
								"value": "eyJhbGciOiJIUzI1NiIsInR5cCI6IkpXVCJ9.eyJpZCI6IjY1N2Y1YWJjOGQzNjNjZTc3MGQwZmQwZiIsImVtYWlsIjoiY2VjaWxlQGdtYWlsLmNvbSIsImlhdCI6MTcwMjg0NTE0OCwiZXhwIjoxNzAyODgxMTQ4fQ.LhbFQcJsglpVkmviy5dCzRRcDItWHueGxcSpPZpOST4",
								"type": "text"
							}
						],
						"url": {
							"raw": "localhost:3003/groups/members/657f5c6565ca9d288d9281e4",
							"host": [
								"localhost"
							],
							"port": "3003",
							"path": [
								"groups",
								"members",
								"657f5c6565ca9d288d9281e4"
							]
						}
					},
					"response": []
				},
				{
					"name": "All Members Of A Group And Accept",
					"request": {
						"method": "GET",
						"header": [
							{
								"key": "Authorization",
								"value": "eyJhbGciOiJIUzI1NiIsInR5cCI6IkpXVCJ9.eyJpZCI6IjY1N2Y1YWJjOGQzNjNjZTc3MGQwZmQwZiIsImVtYWlsIjoiY2VjaWxlQGdtYWlsLmNvbSIsImlhdCI6MTcwMjg0NTE0OCwiZXhwIjoxNzAyODgxMTQ4fQ.LhbFQcJsglpVkmviy5dCzRRcDItWHueGxcSpPZpOST4",
								"type": "text"
							}
						],
						"url": {
							"raw": "localhost:3003/groups/members/accept/657f5c6565ca9d288d9281e4",
							"host": [
								"localhost"
							],
							"port": "3003",
							"path": [
								"groups",
								"members",
								"accept",
								"657f5c6565ca9d288d9281e4"
							]
						}
					},
					"response": []
				},
				{
					"name": "All Groups of user",
					"request": {
						"method": "GET",
						"header": [
							{
								"key": "Authorization",
								"value": "eyJhbGciOiJIUzI1NiIsInR5cCI6IkpXVCJ9.eyJpZCI6IjY1N2Y1YWNiOGQzNjNjZTc3MGQwZmQxNSIsImVtYWlsIjoiY2VjZUBnbWFpbC5jb20iLCJpYXQiOjE3MDI4NDY3MTgsImV4cCI6MTcwMjg4MjcxOH0.iIN20Ml5cNxkdic37iWU8ktYG2_6WdWMt7oEssEVMWU",
								"type": "text"
							}
						],
						"url": {
							"raw": "localhost:3003/groups/members/user/657f5acb8d363ce770d0fd15",
							"host": [
								"localhost"
							],
							"port": "3003",
							"path": [
								"groups",
								"members",
								"user",
								"657f5acb8d363ce770d0fd15"
							]
						}
					},
					"response": []
				}
			]
		}
	]
}